mezzanine_page_auth/__init__.py
mezzanine_page_auth/__init__.pyc
mezzanine_page_auth/admin.py
mezzanine_page_auth/admin.pyc
mezzanine_page_auth/context_processors.py
mezzanine_page_auth/context_processors.pyc
mezzanine_page_auth/middleware.py
mezzanine_page_auth/middleware.pyc
mezzanine_page_auth/models.py
mezzanine_page_auth/models.pyc
mezzanine_page_auth/views.py
mezzanine_page_auth/custom_templates/pages/menus/dropdown.html
mezzanine_page_auth/custom_templates/pages/menus/footer.html
mezzanine_page_auth/custom_templates/pages/menus/footer_tree.html
mezzanine_page_auth/custom_templates/pages/menus/primary.html
mezzanine_page_auth/custom_templates/pages/menus/tree.html
mezzanine_page_auth/locale/it/LC_MESSAGES/django.mo
mezzanine_page_auth/locale/it/LC_MESSAGES/django.po
mezzanine_page_auth/migrations/0001_initial.py
mezzanine_page_auth/migrations/0001_initial.pyc
mezzanine_page_auth/migrations/0002_auto__add_unique_pageauthgroup_page_group.py
mezzanine_page_auth/migrations/0002_auto__add_unique_pageauthgroup_page_group.pyc
mezzanine_page_auth/migrations/__init__.py
mezzanine_page_auth/migrations/__init__.pyc
mezzanine_page_auth/tests/__init__.py
mezzanine_page_auth/tests/__init__.pyc
mezzanine_page_auth/tests/factories.py
mezzanine_page_auth/tests/factories.pyc
mezzanine_page_auth/tests/test_admin.py
mezzanine_page_auth/tests/test_admin.pyc
mezzanine_page_auth/tests/test_middleware.py
mezzanine_page_auth/tests/test_middleware.pyc
mezzanine_page_auth/tests/test_models.py
mezzanine_page_auth/tests/test_models.pyc
mezzanine_page_auth-0.3.3.dist-info/DESCRIPTION.rst
mezzanine_page_auth-0.3.3.dist-info/METADATA
mezzanine_page_auth-0.3.3.dist-info/metadata.json
mezzanine_page_auth-0.3.3.dist-info/RECORD
mezzanine_page_auth-0.3.3.dist-info/top_level.txt
mezzanine_page_auth-0.3.3.dist-info/WHEEL
project_template/__init__.py
project_template/local_settings.py
project_template/manage.py
project_template/settings.py
project_template/urls.py
